caddie/__init__.py
caddie/anm.py
caddie/cisc.py
caddie/measures.py
caddie/scomp.py
caddie/simulations.py
caddie-0.1.6.dist-info/LICENSE
caddie-0.1.6.dist-info/METADATA
caddie-0.1.6.dist-info/WHEEL
caddie-0.1.6.dist-info/top_level.txt
caddie-0.1.6.dist-info/RECORD
