Metadata-Version: 2.1
Name: caddie
Version: 0.1.6
Summary: Information-Theoretic Causal Inference on Discrete Data
Home-page: https://github.com/kailashbuki/caddie
Author: Kailash Budhathoki
Author-email: kailash.buki@gmail.com
License: MIT License
Platform: UNKNOWN
Classifier: Development Status :: 4 - Beta
Classifier: Intended Audience :: Science/Research
Classifier: Topic :: Software Development :: Libraries :: Python Modules
Classifier: License :: OSI Approved :: MIT License
Classifier: Programming Language :: Python :: 3
Classifier: Operating System :: OS Independent
Requires-Python: >=3.7
Requires-Dist: tqdm
Requires-Dist: pandas
Requires-Dist: numpy
Requires-Dist: scipy
Requires-Dist: pytest
